[
    {
        "app_name": "Code.exe",
        "window_title": "Building Drift",
        "activity_type": "Coding",
        "start_time": "2026-06-19T10:00:00",
        "end_time": "2026-06-19T10:05:00",
        "duration_seconds": 300,
        "key_count": 200,
        "mouse_count": 50
    },
    {
        "app_name": "Code.exe",
        "window_title": "Building Drift",
        "activity_type": "Coding",
        "start_time": "2026-06-19T10:00:00",
        "end_time": "2026-06-19T10:05:00",
        "duration_seconds": 300,
        "key_count": 200,
        "mouse_count": 50
    }
]